mdgen/__init__.py
mdgen/constants.py
mdgen/core/__init__.py
mdgen/core/blockquote.py
mdgen/core/bold.py
mdgen/core/code.py
mdgen/core/header.py
mdgen/core/horizontalrule.py
mdgen/core/image.py
mdgen/core/italic.py
mdgen/core/link.py
mdgen/core/lister.py
mdgen/core/table.py
mdgen/core/text.py
mdgen/generator.py
mdgen/main.py
mdgen/markdown.py
mdgen/provider.py
mdgen-0.1.10.dist-info/LICENSE.md
mdgen-0.1.10.dist-info/WHEEL
mdgen-0.1.10.dist-info/METADATA
mdgen-0.1.10.dist-info/RECORD
