Metadata-Version: 2.1
Name: mdgen
Version: 0.1.10
Summary: A library to generate random markdown text
Home-page: https://ignisda.github.io/python-random-markdown-generator/
License: Apache-2.0
Keywords: fake-data,faker,markdown,posts
Author: IgnisDa
Author-email: ignisda2002@gmail.com
Maintainer: IgnisDa
Maintainer-email: ignisda2002@gmail.com
Requires-Python: >=3.6,<4.0
Classifier: License :: OSI Approved :: Apache Software License
Classifier: Operating System :: OS Independent
Classifier: Programming Language :: Python :: 3
Classifier: Programming Language :: Python :: 3.10
Classifier: Programming Language :: Python :: 3.6
Classifier: Programming Language :: Python :: 3.7
Classifier: Programming Language :: Python :: 3.8
Classifier: Programming Language :: Python :: 3.9
Requires-Dist: Faker
Project-URL: Repository, https://github.com/IgnisDa/python-random-markdown-generator/
